mediatimestamp/__init__.py
mediatimestamp/__main__.py
mediatimestamp/_version.py
mediatimestamp/constants.py
mediatimestamp/count_range.py
mediatimestamp/exceptions.py
mediatimestamp/py.typed
mediatimestamp/time_value.py
mediatimestamp/time_value_range.py
mediatimestamp/hypothesis/__init__.py
mediatimestamp/hypothesis/py.typed
mediatimestamp/hypothesis/strategies.py
mediatimestamp/immutable/__init__.py
mediatimestamp/immutable/_parse.py
mediatimestamp/immutable/_types.py
mediatimestamp/immutable/py.typed
mediatimestamp/immutable/timeoffset.py
mediatimestamp/immutable/timerange.py
mediatimestamp/immutable/timestamp.py
mediatimestamp-5.1.0.dist-info/LICENSE.md
mediatimestamp-5.1.0.dist-info/METADATA
mediatimestamp-5.1.0.dist-info/NOTICE.md
mediatimestamp-5.1.0.dist-info/WHEEL
mediatimestamp-5.1.0.dist-info/top_level.txt
mediatimestamp-5.1.0.dist-info/RECORD
