Metadata-Version: 2.1
Name: mediatimestamp
Version: 5.1.0
Summary: A timestamp library for high precision nanosecond timestamps
Home-page: https://github.com/bbc/rd-apmm-python-lib-mediatimestamp
Author: BBC R&D
Author-email: cloudfit-opensource@rd.bbc.co.uk
License: Apache 2
Requires-Python: >=3.10.0
License-File: LICENSE.md
License-File: NOTICE.md
Requires-Dist: python-dateutil>=2.1
Requires-Dist: deprecated
